bookstore/__init__.py
bookstore/exceptions/__init__.py
bookstore/exceptions/book_exceptions.py
bookstore/models/__init__.py
bookstore/models/book.py
bookstore/repositories/__init__.py
bookstore/repositories/book_repository.py
nelson_semtec_bookstore-0.1.0.dist-info/LICENSE
nelson_semtec_bookstore-0.1.0.dist-info/METADATA
nelson_semtec_bookstore-0.1.0.dist-info/WHEEL
nelson_semtec_bookstore-0.1.0.dist-info/top_level.txt
nelson_semtec_bookstore-0.1.0.dist-info/RECORD
