Metadata-Version: 2.1
Name: nelson_semtec_bookstore
Version: 0.1.0
Summary: A demonstration package for teaching Python best practices
Author: RSE Team
License: MIT License
Requires-Python: >=3.8
License-File: LICENSE
Provides-Extra: dev
Requires-Dist: pytest>=7.0; extra == "dev"
Requires-Dist: black>=22.0; extra == "dev"
Requires-Dist: isort>=5.0; extra == "dev"
Requires-Dist: mypy>=1.0; extra == "dev"
